hjcalc/calculator.py
hjcalc/setup.py
hjcalc/tengudan.py
jeongin2024-0.0.1.dist-info/METADATA
jeongin2024-0.0.1.dist-info/WHEEL
jeongin2024-0.0.1.dist-info/top_level.txt
jeongin2024-0.0.1.dist-info/RECORD
